pydradis3/__init__.py
pydradis3/test.py
pydradis3-0.2.3.dist-info/METADATA
pydradis3-0.2.3.dist-info/RECORD
pydradis3-0.2.3.dist-info/WHEEL
pydradis3-0.2.3.dist-info/top_level.txt
