Metadata-Version: 2.1
Name: pydradis3
Version: 0.2.3
Summary: Update of pydradis for Python3 plus some optimizations
Home-page: https://github.com/GoVanguard/pydradis3
Author: Shane Scott
Author-email: sscott@gvit.com
License: UNKNOWN
Platform: UNKNOWN
Classifier: Development Status :: 3 - Alpha
Classifier: Intended Audience :: Developers
Classifier: License :: OSI Approved :: GNU General Public License v2 (GPLv2)
Classifier: Programming Language :: Python :: 3.6
Classifier: Operating System :: OS Independent
